{
  "myPokemon": [
    {
      "url": "https://pokeapi.co/api/v2/pokemon/5/",
      "id": 1
    },
    {
      "url": "https://pokeapi.co/api/v2/pokemon/2/",
      "id": 2
    },
    {
      "url": "https://pokeapi.co/api/v2/pokemon/151/",
      "id": 3
    },
    {
      "url": "https://pokeapi.co/api/v2/pokemon/8/",
      "id": 4
    },
    {
      "url": "https://pokeapi.co/api/v2/pokemon/87/",
      "id": 9
    },
    {
      "url": "https://pokeapi.co/api/v2/pokemon/17/",
      "id": 10
    },
    {
      "url": "https://pokeapi.co/api/v2/pokemon/25/",
      "id": 11
    }
  ]
}